elastic_training/__init__.py
elastic_training/adapter.py
elastic_training/preemption_detector.py
elastic_training-0.0.2.dist-info/LICENSE
elastic_training-0.0.2.dist-info/METADATA
elastic_training-0.0.2.dist-info/WHEEL
elastic_training-0.0.2.dist-info/top_level.txt
elastic_training-0.0.2.dist-info/RECORD
