Metadata-Version: 2.1
Name: elastic-training
Version: 0.0.2
Summary: A small example package
Home-page: https://github.com/pengwa/elastic-training
Author: Peng Wang
Author-email: pengwa@microsoft.com
License: UNKNOWN
Platform: UNKNOWN
Classifier: Programming Language :: Python :: 3
Classifier: License :: OSI Approved :: MIT License
Classifier: Operating System :: OS Independent
Requires-Python: >=3.6
Requires-Dist: watchdog
Requires-Dist: logger
